Metadata-Version: 1.1
Name: sgp30
Version: 0.1.4
Summary: Library for reading data from the sensiron SGP30
Home-page: https://github.com/zinob/RPI_SGP30
Author: Simon Albinsson
Author-email: pipmon@zinob.se
License: MIT
Keywords: sgp30 i2c smbus smbus2
Platform: UNKNOWN
Classifier: Development Status :: 4 - Beta
Classifier: Intended Audience :: Developers
Classifier: License :: OSI Approved :: MIT License
